aiide/__init__.py
aiide/_aiide.py
aiide/_utils.py
aiide/schema/__init__.py
aiide/schema/_definitions.py
aiide-0.0.8.dist-info/LICENSE
aiide-0.0.8.dist-info/METADATA
aiide-0.0.8.dist-info/WHEEL
aiide-0.0.8.dist-info/RECORD
