Metadata-Version: 2.1
Name: aiide
Version: 0.0.8
Summary: aiide is a framework to build LLM copilots.
Home-page: https://github.com/Anilturaga/aiide
License: Apache-2.0
Keywords: llm,openai
Author: Anilturaga
Requires-Python: >=3.10,<4.0
Classifier: License :: OSI Approved :: Apache Software License
Classifier: Programming Language :: Python :: 3
Classifier: Programming Language :: Python :: 3.10
Classifier: Programming Language :: Python :: 3.11
Classifier: Programming Language :: Python :: 3.12
Requires-Dist: litellm (>=1.52.16,<2.0.0)
Requires-Dist: pandas (>=2.2.2,<3.0.0)
Requires-Dist: pillow (>=10.4.0,<11.0.0)
Requires-Dist: pyarrow (>=17.0.0,<18.0.0)
Project-URL: Repository, https://github.com/Anilturaga/aiide
